{
  "chapter_index": 10,
  "chapter_title": "穷人思维和富人思维，决定你一生的财富",
  "core_points": [
    "穷人思维的核心是人性的不耐和懒惰，而这决定了一生的财富",
    "持有能产生现金流的资产是脱贫致富的基本道理（如养鸡）",
    "即便拥有好资产，缺乏耐心和坚持也无法致富",
    "消费是即时享受，投资需要时间沉淀，需要足够耐心",
    "自己本身就是能产生现金流的资产，需要通过劳动去努力提升"
  ],
  "arguments": [],
  "actionables": [
    "投资要趁早，越早开始越好",
    "30岁之前优先提升自己，租房尽量住得离工作近、离钱近",
    "人到中年规划家庭消费：可选消费降级，必需消费走量",
    "克服人性的不耐与懒惰，保持耐心与坚守"
  ],
  "quotes": [
    "这就是最简单的“持有资产致富”的道理。",
    "人性的不耐和懒惰，就是穷人思维的核心。",
    "但凡要饭的，没有要早饭的，因为他要是能早起，就不至于要饭。",
    "我们自己也是一个可以产生现金流的资产，自己不努力，这个资产的价值就会大大缩水。",
    "所以要想脱贫，就必然得忍受很久一段时间的贫穷，而这种品质叫作坚守！",
    "人性的不耐和懒惰，是人们陷入贫穷的根本原因。我们想要变得富有，就不能犯同样的错误。"
  ],
  "opinions": [
    {
      "opinion": "持有能产生现金流的资产是致富的最简单道理，投资理财与之性质相同",
      "chapter": "穷人思维和富人思维，决定你一生的财富",
      "tags": [
        "复利",
        "资产配置"
      ],
      "argument_summary": "以养鸡为例，鸡是能产生现金流的资产，养5只鸡三个月成群，最终每年可赚超1000美元，超过极端贫困水平。这与投资理财性质相同。",
      "actionability": "原则",
      "quote": "这就是最简单的“持有资产致富”的道理。"
    },
    {
      "opinion": "人性的不耐是穷人思维的核心，极端没有耐心的人无法等待资产产生现金流",
      "chapter": "穷人思维和富人思维，决定你一生的财富",
      "tags": [
        "市场心理",
        "投资纪律"
      ],
      "argument_summary": "扶贫送小鸡但贫困户因缺乏耐心把鸡吃掉，无法等待资产产生现金流；很多人没有富有是因为缺乏忍受贫穷、坚持奋斗的耐心。",
      "actionability": "原则",
      "quote": "人性的不耐和懒惰，就是穷人思维的核心。"
    },
    {
      "opinion": "任何投资都需要时间沉淀，消费永远比投资容易，致富必须有足够耐心和坚守",
      "chapter": "穷人思维和富人思维，决定你一生的财富",
      "tags": [
        "复利",
        "投资纪律"
      ],
      "argument_summary": "消费不需要等待是即时享受，而投资需要时间沉淀，所以致富必须忍受较长时间的贫穷并坚守。",
      "actionability": "原则",
      "quote": "任何情况下，消费都比投资更容易。因为消费不需要等待，是一种即时享受。但是同样的钱，去做任何一种投资，都需要时间的沉淀。"
    },
    {
      "opinion": "自己本身就是能产生现金流的资产，需通过劳动努力提升，否则资产价值缩水",
      "chapter": "穷人思维和富人思维，决定你一生的财富",
      "tags": [
        "资产配置"
      ],
      "argument_summary": "懒惰是不想贡献人力资产只想不劳而获；自己本身也是产生现金流的资产，不努力资产价值会缩水，这也是大多数人需要上班的原因。",
      "actionability": "原则",
      "quote": "我们自己也是一个可以产生现金流的资产，自己不努力，这个资产的价值就会大大缩水。"
    },
    {
      "opinion": "应趁早投资，30岁前优先提升自己、住得离工作和钱近，中年时可选消费降级、必需消费走量",
      "chapter": "穷人思维和富人思维，决定你一生的财富",
      "tags": [
        "资产配置",
        "复利"
      ],
      "argument_summary": "作者在投资者笔记中给出针对不同年龄阶段的具体建议：趁早投资、年轻时提升自己并住得离钱近、中年时可选消费降级必需消费走量。",
      "actionability": "可直接执行",
      "quote": "30岁之前，优先提升自己。如果要租房，尽量住得离工作近一点，住得离钱近一点。"
    },
    {
      "opinion": "直接送资产未必有效，需结合自身能力主动参与和坚持，否则可能养成懒惰",
      "chapter": "穷人思维和富人思维，决定你一生的财富",
      "tags": [
        "投资纪律"
      ],
      "argument_summary": "扶贫经验总结认为对贫困人员最好以富带贫、通过产业项目吸纳其从事力所能及的工作，直接送资产可能养懒汉。",
      "actionability": "需自己判断",
      "quote": "对于贫困人员，最好是以富带贫，通过发展产业项目，把贫困人员吸纳进来，让他们从事力所能及的工作，通过报酬来解决贫困问题。否则，只能养懒汉。"
    }
  ],
  "suggested_tags": [
    "建议新增：财富心态",
    "建议新增：人力资本"
  ]
}