{
  "chapter_index": 3,
  "chapter_title": "序言",
  "core_points": [
    "A股有优质基金品种能提供长期高回报，但大部分投资者难以赚钱",
    "投资者亏钱的主因是在牛市高位追涨、投入全部资金",
    "定投是分散投资，能降低风险，长期坚持大概率赚钱",
    "定投的最大难点是在动荡市场中坚持",
    "在熊市低迷时定投，买得不贵、长期坚持，赚钱水到渠成"
  ],
  "arguments": [
    "A股'七亏二平一赚'的主要原因是大部分投资者在4000点以上、身边人都赚钱时才买入，涨得越多买得越多",
    "很多人在2007年和2015年牛市高位开户并投入全部资金，之后市场下跌导致收益不佳",
    "定投是分散投资，投资者不会在牛市高位投入全部资金，风险大大降低",
    "巴菲特说过通过定投指数基金，业余投资者也能战胜大部分专业投资者",
    "坚持定投最难，银行螺丝钉五年写近千篇文章、每日发布估值表帮助投资者坚持"
  ],
  "actionables": [
    "在市场估值低、熊市低迷时开始定投，避免在牛市高位一次性投入全部资金",
    "坚持长期定投，不因市场动荡而中断",
    "作为普通投资者或上班族，可通过定投指数基金来配置收入"
  ],
  "quotes": [
    "很多老股民说A股“七亏二平一赚”，还是很有道理的。",
    "许多投资者不知道股票品种的风险，涨得越多，买得越多。",
    "通过定投指数基金，一个什么都不懂的业余投资者，竟然能够战胜大部分专业投资者。",
    "定投是分散投资，定投的投资者不可能在牛市高位投入全部资金，风险自然大大降低。",
    "但是定投说起来容易，做起来难。",
    "买得不贵，长期坚持，赚钱也就水到渠成了。",
    "念念不忘，必有回响。"
  ],
  "opinions": [
    {
      "opinion": "大部分投资者难以在股票基金上赚钱，A股'七亏二平一赚'确实存在",
      "chapter": "序言",
      "tags": [
        "市场心理",
        "风险控制"
      ],
      "argument_summary": "老股民常说A股'七亏二平一赚'，作者认为很有道理，主因是投资者高位追涨。",
      "actionability": "原则",
      "quote": "很多老股民说A股“七亏二平一赚”，还是很有道理的。"
    },
    {
      "opinion": "投资者亏钱的重要原因是在牛市高位、看到别人赚钱后才追涨买入",
      "chapter": "序言",
      "tags": [
        "市场心理",
        "择时",
        "风险控制"
      ],
      "argument_summary": "投资者往往在牛市火热、身边人赚钱时才入场，2007和2015年牛市高位开户投入全部资金，之后下跌亏损。",
      "actionability": "原则",
      "quote": "绝大部分投资者是在A股4000点以上，看到身边的亲戚朋友都赚钱了，才开始买股票基金的。"
    },
    {
      "opinion": "涨得越多买得越多、在高位投入全部资金是导致收益不理想的错误行为",
      "chapter": "序言",
      "tags": [
        "仓位管理",
        "风险控制",
        "市场心理"
      ],
      "argument_summary": "许多投资者不知道股票风险，涨得越多买得越多，在高位投入全部资金后下跌。",
      "actionability": "原则",
      "quote": "许多投资者不知道股票品种的风险，涨得越多，买得越多。他们在牛市高位投入全部资金，之后市场下跌，收益自然不理想。"
    },
    {
      "opinion": "定投能改变投资者不赚钱的状况，因为它分散投资、降低了高位一次性投入的风险",
      "chapter": "序言",
      "tags": [
        "分散化",
        "风险控制",
        "投资纪律"
      ],
      "argument_summary": "定投是分散投资，投资者不可能在牛市高位投入全部资金，能长期坚持大概率赚钱。",
      "actionability": "可直接执行",
      "quote": "定投是分散投资，定投的投资者不可能在牛市高位投入全部资金，风险自然大大降低。能长期坚持定投，最后大概率是赚钱的。"
    },
    {
      "opinion": "通过定投指数基金，业余投资者也能战胜大部分专业投资者",
      "chapter": "序言",
      "tags": [
        "复利",
        "分散化"
      ],
      "argument_summary": "引用巴菲特观点说明定投指数基金的有效性。",
      "actionability": "原则",
      "quote": "通过定投指数基金，一个什么都不懂的业余投资者，竟然能够战胜大部分专业投资者。"
    },
    {
      "opinion": "定投的最大难点在于坚持，尤其在动荡市场环境中",
      "chapter": "序言",
      "tags": [
        "投资纪律",
        "市场心理"
      ],
      "argument_summary": "定投说起来容易做起来难，大部分投资者难以在动荡市场中坚持，需要自己克服。",
      "actionability": "需自己判断",
      "quote": "大部分投资者是难以在动荡的市场环境中做到坚持定投的。如何坚持下来，是投资者定投时面临的最大难点。"
    },
    {
      "opinion": "应在熊市低迷时定投，买得不贵、长期坚持，赚钱水到渠成",
      "chapter": "序言",
      "tags": [
        "安全边际",
        "择时",
        "投资纪律"
      ],
      "argument_summary": "在熊市低迷时定投能解决牛市高位买入亏钱的痛点，买得不贵长期坚持自然赚钱。",
      "actionability": "可直接执行",
      "quote": "帮助大家在熊市低迷的时候定投基金，这在很大程度上解决了投资者“牛市高位买入亏钱”的痛点。买得不贵，长期坚持，赚钱也就水到渠成了。"
    }
  ],
  "suggested_tags": [
    "建议新增：定投"
  ]
}