{
  "chapter_index": 39,
  "chapter_title": "第39段",
  "core_points": [
    "以接近或高于面值销售的附权高级证券，必须明确符合纯粹固定价值投资或纯粹普通股投机之一，不应有中间立场",
    "反对在纯粹投资与彻底投机之间妥协，因为这会导致混乱、模糊和自欺欺人，购买者对自己承担风险的目的不明确",
    "保守的附权证券购买者升值空间通常不超过25%~35%，真正成功的可转换债券投资持有时间不会很长",
    "一般情况下投资者不应转换可转换债券，而应将其持有或出售，以免放弃对本金及利息的优先权并从投资者沦为投机者",
    "评估分红特权吸引力取决于安排的条款和可分红的前景两个不相关因素，选择正确的公司比选择更好的条款更有利可图",
    "考察分红特权应关注三个要素：每美元的投机获利数额、特权与可实现利润的接近程度、特权的存续期",
    "低价大量兑换股票的投机收益在技术上比高价少量兑换更具吸引力，因低价股更易大幅波动"
  ],
  "arguments": [
    "1927年兰德·卡德克斯并购雷明顿后股票涨至76美元、债券涨至190美元，说明优质附权债券在企业向好时利润丰厚",
    "国内贸易杂志公司债券的估计收益近一半来自减薪等盘整手段的预期收益，安全性不足，最终清算后每1美元面值仅得约8.5美分补偿",
    "中间立场会导致投资者在损失时财政与精神都没做好准备，投机者则分不清自己是股票还是债券持有人",
    "转换后若情况变糟，股票价值可能跌至远低于原购债成本，损失的不仅是利润还有本金",
    "B公司转换条款更优（股价只需涨3点获利），但A公司可能更好，因为A股票可能翻番而B股票根本不涨",
    "俄亥俄铜业公司7%债券可按1美元兑换1000股，1928年股价不足1美元到1929年涨到4.875美元，债券价值达面值近500%，说明低价大量兑换股票的投机潜力更大",
    "洲际橡胶债券每1000美元可获投机收益5000美元，若120美元卖出则收益达投资额417%，是可靠百货60美元收益的70倍，说明投机收益数额差异巨大"
  ],
  "actionables": [
    "购买以接近或高于面值销售的附权高级证券前，先判断它是否明确符合纯粹固定价值投资标准，或纯粹普通股投机标准，二者必居其一，拒绝中间立场",
    "作为安全债券投资购买的附权证券，升值达到25%~35%区间即应卖出，且此后即使价格继续上涨也不动摇判断",
    "一般情况下不要行使可转换债券的转换权，应持有或卖出，以保留对本金及利息的优先权",
    "以纯粹投机目的购买的附权证券，卖出理由应基于对普通股是否已达足够涨幅的判断，而非债券本身的溢价幅度",
    "评估附权证券时考察三要素：每美元的投机获利数额、购买时特权与可实现利润的接近程度、特权的存续期",
    "在企业质量与特权条款之间，优先选择正确的公司而非更优的转换条款",
    "持续更换售价接近面值的新可转换债券，以获利后不断再投资"
  ],
  "quotes": [
    "以接近或高于面值的价格销售的附权高级证券，必须要么符合纯粹固定价值投资的要求，要么符合纯粹普通股投机的要求，必须明显具备两者之一才可以购买。",
    "对本金的安全性感兴趣的投资者不应降低要求，以换取转换特权；投机者也不应被债券合同所提供的安全的假象所吸引而投资一个预计获利不高的企业。",
    "如果采取中间立场，那么其结果通常是混乱、模糊和自欺欺人。",
    "一般情况下，投资者不应转换可转换债券，而应将其持有或出售。",
    "当所持债券价格已超过投资的价格波幅时，他必须将其卖出；最重要的是，即使债券的价格随后上升到高得多的水平，他也不能怀疑自己的判断。",
    "在这两个因素之间，毫无疑问，更有利可图的选择是选择正确的公司，而不是选择更令人满意的条款。",
    "大量、低价卖出股票的投机收益，从技术上说比少量、高价卖出股票更具吸引力。",
    "即便是良好的可转换债券也存在潜在的风险；它对于粗心大意的人来说很容易成为代价高昂的圈套。"
  ],
  "opinions": [
    {
      "opinion": "以接近或高于面值销售的附权高级证券，必须明确符合纯粹固定价值投资标准或纯粹普通股投机标准之一，不应有任何中间立场。",
      "chapter": "第39段",
      "tags": [
        "安全边际",
        "风险控制",
        "投资纪律",
        "opinion",
        "tags",
        "argument_summary",
        "actionability",
        "quote"
      ],
      "argument_summary": "作者以联邦爱迪生、切萨皮克和俄亥俄铁路、兰德·卡德克斯等优质债券与国内贸易杂志公司的劣质债券对比，指出中间立场会导致投资者与投机者双双准备不足、目的不明。",
      "actionability": "原则",
      "quote": "以接近或高于面值的价格销售的附权高级证券，必须要么符合纯粹固定价值投资的要求，要么符合纯粹普通股投机的要求，必须明显具备两者之一才可以购买。"
    },
    {
      "opinion": "应反对在纯粹投资和彻底投机之间做出妥协的态度，因为其结果通常是混乱、模糊和自欺欺人。",
      "chapter": "第39段",
      "tags": [
        "投资纪律",
        "市场心理",
        "风险控制"
      ],
      "argument_summary": "若采取妥协态度，放松安全性的投资者在损失时财政与精神都未准备好，而降低风险的投机者会分不清自己的角色。",
      "actionability": "原则",
      "quote": "如果采取中间立场，那么其结果通常是混乱、模糊和自欺欺人。"
    },
    {
      "opinion": "对企业公布的估计收益要保持怀疑，尤其当收益大量来自减薪等盘整手段的预期时，不应视为理所当然。",
      "chapter": "第39段",
      "tags": [
        "财报分析",
        "安全边际",
        "风险控制"
      ],
      "argument_summary": "国内贸易杂志公司的估计收益近一半来自减薪等盘整手段，保守投资者不应视为理所当然，尤其在竞争激烈、有形资产少的企业。",
      "actionability": "需自己判断",
      "quote": "保守的投资者不会认为这些"
    },
    {
      "opinion": "作为安全债券投资购买的附权证券，升值达到约25%~35%即应卖出，且此后即使价格继续上涨也不能怀疑自己的判断。",
      "chapter": "第39段",
      "tags": [
        "择时",
        "投资纪律",
        "风险控制"
      ],
      "argument_summary": "保守的附权证券购买者升值空间通常不超过25%~35%，因此成功运作持有时间不会很长，超过投资价格波幅就应卖出。",
      "actionability": "可直接执行",
      "quote": "当所持债券价格已超过投资的价格波幅时，他必须将其卖出；最重要的是，即使债券的价格随后上升到高得多的水平，他也不能怀疑自己的判断。"
    },
    {
      "opinion": "一般情况下投资者不应转换可转换债券，而应将其持有或出售。",
      "chapter": "第39段",
      "tags": [
        "风险控制",
        "投资纪律",
        "安全边际"
      ],
      "argument_summary": "转换后放弃了对本金及利息的优先权和无条件要求权，若情况变糟股票可能跌至远低于购债成本，损失本金并从投资者变为投机者。",
      "actionability": "原则",
      "quote": "一般情况下，投资者不应转换可转换债券，而应将其持有或出售。"
    },
    {
      "opinion": "在企业质量与转换条款之间，选择正确的公司比选择更好的条款更有利可图，但市场价格通常已反映企业优势。",
      "chapter": "第39段",
      "tags": [
        "估值",
        "护城河/竞争优势",
        "市场心理"
      ],
      "argument_summary": "股票市场价格通常已反映企业间的优势差异，投资者若因预期某股涨幅更大而选债，就是在缺乏确定性、必然错误频出的领域做独立判断。",
      "actionability": "需自己判断",
      "quote": "在这两个因素之间，毫无疑问，更有利可图的选择是选择正确的公司，而不是选择更令人满意的条款。"
    },
    {
      "opinion": "在安全性高的前提下，能低价兑换大量股票的债券比高价少量兑换的更具投机吸引力，因低价股更易大幅波动。",
      "chapter": "第39段",
      "tags": [
        "风险控制",
        "估值",
        "市场心理"
      ],
      "argument_summary": "以俄亥俄铜业公司与艾奇逊铁路债券对比，低价大量兑换的债券股价更易大幅波动，可通过短期投机操作获得高额利润。",
      "actionability": "需自己判断",
      "quote": "大量、低价卖出股票的投机收益，从技术上说比少量、高价卖出股票更具吸引力。"
    },
    {
      "opinion": "评估附权证券的分红特权吸引力取决于两个完全不相关的因素：安排的条款和可以分红的前景。",
      "chapter": "第39段",
      "tags": [
        "估值",
        "安全边际"
      ],
      "argument_summary": "作者指出分红特权吸引力取决于安排的条款和可分红的前景两个完全不相关的因素，需分别评估。",
      "actionability": "原则",
      "quote": "分红制特点的吸引力取决于两个主要的，但完全不相关的因素"
    }
  ],
  "suggested_tags": [
    "建议新增：可转换债券/附权证券"
  ]
}