{
  "chapter_index": 9,
  "chapter_title": "第一章　证券",
  "core_points": [
    "证券是表明财产所有权或债权的凭证，有价证券的本质在于表明一定财产权且可参与流通，是金融工具和投资凭证",
    "有价证券是资本的'纸制复本'，具有虚拟资本性质，本身没有价值，只代表取得收益的权利，间接反映实际资本运动",
    "股票具有不返还性、风险性、流通性三大特征，代表股份资本所有权",
    "股票价值有票面价值、账面价值、市场价值、清算价值、内在价值多种形式，市场价值与账面价值无必然联系",
    "市盈率和市净率是衡量股价高低和投资价值的重要指标",
    "债券是承诺按期付息还本的债务凭证，具有流动性、收益性、风险性、返还性四大特征",
    "债券的风险性、收益性、流动性之间存在相互补偿关系",
    "债券收益用收益率衡量，主要有当期收益率、到期收益率、最终收益率三种测度方法",
    "债券价格等于预期现金流量的现值，与市场利率成反比",
    "债券投资面临利率风险、再投资风险、赎回风险、违约风险、通货膨胀风险、流动性风险、波动性风险等多种风险"
  ],
  "arguments": [
    "有价证券本身没有价值，只代表取得收益的权利，不在生产过程中发挥作用，是资本的符号代表即虚拟资本，只间接反映实际资本的运动",
    "虚拟资本数量等于各种有价证券的价格总额，一般情况下总是大于实际资本额，其变化不一定反映实际资本总额的变化",
    "股票具有不返还性、风险性、流通性三大特征，只付息分红不退还本金，风险共担收益共享，可转让抵押买卖",
    "市场价值受股利分配、公司收益、前景、预期、供求、经济形势等多种因素影响，与账面价值没有必然联系",
    "市盈率把股价和企业盈利能力结合起来，反映股价高低更真实；预期利润增长率高的公司市盈率也会较高",
    "债券风险低于股票：利率固定不受盈利影响、有法律保障、发行者经严格选择、破产时债权人优先于股东获清偿",
    "债券的风险性、收益性、流动性之间相互补偿：风险小流动性强则收益低，风险大流动性差则收益高",
    "到期收益率考虑了各期利息、资本利得或损失以及现金流量的时间性，是债券的内部回报率，可比较不同债券收益",
    "债券价格等于其预期现金流量的现值，故债券价格与市场利率成反比",
    "债券期限越长价格波动越大，风险越高；息票利率越高价格变动百分比越低",
    "利率风险与再投资风险此消彼长：利率风险是利率上升导致价格下降的风险，再投资风险是利率下降的风险，以此机理制定免疫策略",
    "市盈率的倒数相当于股市投资的预期利润率，合理市盈率水平与市场利率水平呈倒数关系"
  ],
  "actionables": [
    "计算普通股每股账面价值：净资产减去优先股面值后，除以普通股总股数",
    "用市盈率（当前每股市价/每股税后利润）衡量股价高低和企业盈利能力，估算投资回收年限",
    "用市净率（股票市价/每股净资产）判断投资价值，市净率越低风险相对越低",
    "根据投资目的、期限、财务状况选择债券：长期投资选安全性和收益性好但流动性弱的债券，短期投资选流动性强的债券",
    "若预测市场利率将下跌，可买入债券待价格上涨后卖出赚取价差；预测利率上升则相反操作",
    "厌恶风险者不购买期限过长的债券以规避价格波动风险；投机者可多买长期债券获取投机机会",
    "投资期限较短的债券或同时投资不同到期日的债券可降低利率风险；持有债券到期满可将利率风险降到最低",
    "用信用评级公司出具的信用等级衡量债券违约风险，非国债债券比可比国债有更高收益率",
    "用买价与卖价之间的差额测量债券流动性风险，差额越大流动性风险越大"
  ],
  "quotes": [
    "有价证券不是生产经营的物资，更不能在生产经营过程中发挥作用，因而它不是真正的资本，而是"
  ],
  "opinions": [
    {
      "opinion": "有价证券是'资本的纸制复本'，具有虚拟资本性质，本身没有任何价值，只代表取得收益的权利",
      "chapter": "第一章　证券",
      "tags": [
        "估值",
        "opinion_placeholder"
      ],
      "argument_summary": "有价证券不是真正的资本，只是资本的符号代表，本身无价值，只代表取得收益的权利",
      "actionability": "原则",
      "quote": "构成虚拟资本的有价证券本身没有任何价值。它们只是代表取得收益的权利。"
    }
  ],
  "suggested_tags": []
}