{
  "chapter_index": 38,
  "chapter_title": "index_split_037.html",
  "core_points": [],
  "arguments": [],
  "actionables": [],
  "quotes": [],
  "opinions": [
    {
      "opinion": "优先股处于'两头不占'的弱势法律地位：其安全性依赖公司支付普通股红利的意愿，一旦普通股红利被取消地位便不稳固；同时既无债券持有者的优先索取权，也无普通股持有者分享利润的机会。",
      "chapter": "index_split_037.html",
      "tags": [
        "风险控制",
        "安全边际"
      ],
      "argument_summary": "典型优先股持有者将安全性建立在公司支付普通股的能力和愿望上，一旦普通股红利被取消其地位便不稳定；而它又不参与公司利润分配，因此既缺乏债权人的优先索取权，也缺乏合伙人的获利可能。",
      "actionability": "原则",
      "quote": "典型的优先股持有人既没有债券持有者（或债权人）的决定索取权，也没有普通股持有者（或合伙人）享有的获取利润的可能性。"
    },
    {
      "opinion": "萧条时期优先股法定地位上的弱点更加明显，只有极少数优先股能在整个经济变迁中保持毫无问题的投资地位。",
      "chapter": "index_split_037.html",
      "tags": [
        "风险控制",
        "宏观周期"
      ],
      "argument_summary": "萧条时优先股的法律弱点暴露无遗，经验表明所有优先股中只有一小部分能在整个变迁中保持牢固而毫无问题的投资地位。",
      "actionability": "原则",
      "quote": "在萧条时，优先股法定地位上的这些弱点便更加明显。所有优先股中，只有一小部分使自己处于牢固的地位，在整个变迁中保持一个毫无问题的投资地位。"
    },
    {
      "opinion": "购买优先股的正确时机是临时性逆境使其价格被过分压低时，应在廉价基础上购买或根本不买；此时它适合进取型投资者，不适合防御型投资者。",
      "chapter": "index_split_037.html",
      "tags": [
        "安全边际",
        "择时"
      ],
      "argument_summary": "经验告诉我们，购买优先股的时间是临时性逆境使价格被过分压低之时，此时价格便宜、有安全边际，但这种机会需投资者自行识别与判断，且仅适合能承担风险的进取型投资者。",
      "actionability": "需自己判断",
      "quote": "经验告诉我们，购买优先股的时间，是临时性的逆境使得它们的价格被过分压低时（在这时，它们可能适合于进取的投资者，但不适合于防御型投资者）。它们应该在廉价的基础上被购买，或根本不被购买。"
    },
    {
      "opinion": "公司购买者在优先股上享有远优于个人投资者的纳税地位，因此逻辑上投资等级的优先股应由公司购买，而免税债券应由个人纳税投资者购买。",
      "chapter": "index_split_037.html",
      "tags": [
        "交易成本/税费",
        "资产配置"
      ],
      "argument_summary": "公司对优先股红利收入仅需按15%纳税（100美元红利仅纳7.20美元），而债券利息按48%纳税；个人投资者在优先股上则须承担与债券同样的税负。因此不同持有主体应据纳税地位配置不同证券。",
      "actionability": "需自己判断",
      "quote": "严格地按逻辑讲，所有投资等级的优先股应该由公司购买，就像所有免税债券应该由支付所得税的投资者购买一样。"
    }
  ],
  "suggested_tags": []
}