{
  "chapter_index": 51,
  "chapter_title": "index_split_050.html",
  "core_points": [],
  "arguments": [],
  "actionables": [],
  "quotes": [],
  "opinions": [
    {
      "opinion": "一等与二等债券的关键差别在于公司收益对利息的覆盖倍数；防范良好的铁路债券应要求公司收益高于利息5倍，而案例中仅1.5倍，安全性严重不足。",
      "chapter": "index_split_050.html",
      "tags": [
        "财报分析",
        "安全边际"
      ],
      "argument_summary": "以1963年芝加哥、密尔沃基、圣保罗和太平洋公司债券为例，税前收益仅为利息支出的1.5倍，远低于5倍的期望标准，说明二等债券缺乏足够的收益保护。",
      "actionability": "需自己判断",
      "quote": "1963年铁路税前收益仅是其债券全部利息支出的1.5倍，违背了我们关于有着良好防范的铁路债券其公司收益要高于债券利息5倍的期望。"
    },
    {
      "opinion": "仅仅因为收益诱人而购买缺乏足够安全性的债券或优先股是不明智的，尤其当以接近全价买入、没有大折扣时。",
      "chapter": "index_split_050.html",
      "tags": [
        "安全边际",
        "风险控制"
      ],
      "argument_summary": "以全价购买缺乏安全性的债券，未来看到更低行市的可能性很大；坏业务或坏市场出现时这类债券对下跌极其敏感，利息红利支付常被延期或处于危险中。",
      "actionability": "原则",
      "quote": "经验清楚地表明，仅仅由于收益诱人而去购买缺乏足够安全性的债券或优先股是不明智的"
    },
    {
      "opinion": "为了1%-2%的额外年收入而接受公认的本金损失可能性，是一件坏事；承担风险时应确保事情进展良好时首先能在本金上取得可观收益。",
      "chapter": "index_split_050.html",
      "tags": [
        "安全边际",
        "风险控制"
      ],
      "argument_summary": "1946-1947年10种铁路收入债券案例：高价平均102.5美元，随后低价平均仅68美元，短期损失1/3，跌幅超过道琼斯工业股约23%的跌幅，购买者却只多获得约1.75%的年收入，风险与回报严重不对称。",
      "actionability": "原则",
      "quote": "如果仅仅为了1%或2%额外的年收入，而接受公认的损失本金的可能性，它就是一件坏事情。如果你愿意承担一些风险，你应该肯定，如果事情进展良好，你首先能够在本金值上取得相当大的收益。"
    },
    {
      "opinion": "以账面价值（接近全价）出售、收益率5.5%-6%的二等债券几乎总是坏的购买；有耐心者应等待在70美元左右的折价水平买入。",
      "chapter": "index_split_050.html",
      "tags": [
        "安全边际",
        "择时"
      ],
      "argument_summary": "同样的证券在70美元时才更有意义，既提供了资本增值空间，又缓冲了下行风险；关键在于价格而非收益率本身。",
      "actionability": "需自己判断",
      "quote": "以账面价值出售的收益率为5.5%或6%的二等债券几乎总是一个坏的购买。价格为70美元的同样的证券可能更有意义，如果你有耐心，你将可能在那个水平上购买它。"
    },
    {
      "opinion": "二等债券和优先股具有两个相矛盾的性能：坏市场中几乎都会严重下跌，但好条件重现时大量证券又会回升，因此低价被冷落时买入可能获得丰厚利润。",
      "chapter": "index_split_050.html",
      "tags": [
        "市场心理",
        "安全边际"
      ],
      "argument_summary": "30年代萧条导致40年代初大量优先股多年未付股息，但1945-1947战后繁荣期，许多累积优先股以现金或新证券偿付，几年前低价买入者获得大量利润。",
      "actionability": "需自己判断",
      "quote": "二等债券和优先股拥有两个相矛盾的性能，明智的投资者必须清楚地记在心里。在坏的市场，几乎所有的证券都经受着一段时间的严重下跌；另一方面，当好的条件重现时，大量的证券又重新回到它们的价位。"
    },
    {
      "opinion": "即使统计上以开价买入全部这类证券的投资者最终结果可能与只买一流证券者相当甚至略好，但对无法做到充分分散、也无法承受价格波动焦虑的个人投资者而言，这一统计结论没有实际意义。",
      "chapter": "index_split_050.html",
      "tags": [
        "分散化",
        "市场心理"
      ],
      "argument_summary": "个人投资者无法购买足够多的证券以保证平均结果，也无法从高收入中留出部分来'分期偿还'永久性资本损失；当价格突然下跌时会陷入焦虑和烦恼，因此不能照搬'商人投资'的整体统计逻辑。",
      "actionability": "需自己判断",
      "quote": "无论结果如何，当二等债券的价格突然下跌时，以全价购买它们的购买者将会焦虑和烦恼。更进一步，他不可能购买足够的证券以保证一个平均结果，他也不能够留出大量收入的一部分以弥补或'分期偿还'那些已被证明是永久的资本损失。"
    }
  ],
  "suggested_tags": []
}